Metadata-Version: 2.1
Name: python-probability-distributions
Version: 1.0
Summary: Gaussian and Binomial distributions
Home-page: UNKNOWN
Author: Precious Michael
Author-email: Precious.michael2002@gmail.com
License: UNKNOWN
Platform: UNKNOWN
